heimdall_sp_validator_sdk/__init__.py
heimdall_sp_validator_sdk/cache.py
heimdall_sp_validator_sdk/exceptions.py
heimdall_sp_validator_sdk/models.py
heimdall_sp_validator_sdk/validator.py
heimdall_sp_validator_sdk-0.1.0.dist-info/licenses/LICENSE
heimdall_sp_validator_sdk-0.1.0.dist-info/METADATA
heimdall_sp_validator_sdk-0.1.0.dist-info/WHEEL
heimdall_sp_validator_sdk-0.1.0.dist-info/top_level.txt
heimdall_sp_validator_sdk-0.1.0.dist-info/RECORD
