Metadata-Version: 2.4
Name: heimdall-sp-validator-sdk
Version: 0.1.0
Summary: Service Provider SDK for validating Agent Identity Framework (AIF) tokens
Home-page: https://github.com/IAM-Heimdall/heimdall-sp-validator-sdk-python
Author: IAM Heimdall Team
Author-email: IAM Heimdall Team <contact@iamheimdall.com>
License: MIT
Project-URL: Homepage, https://poc.iamheimdall.com
Project-URL: Documentation, https://github.com/IAM-Heimdall/heimdall-sp-validator-sdk-python/blob/main/README.md
Project-URL: Repository, https://github.com/IAM-Heimdall/heimdall-sp-validator-sdk-python
Project-URL: Issues, https://github.com/IAM-Heimdall/heimdall-sp-validator-sdk-python/issues
Keywords: aif,agent,identity,framework,jwt,token,validation,security
Classifier: Development Status :: 3 - Alpha
Classifier: Intended Audience :: Developers
Classifier: License :: OSI Approved :: MIT License
Classifier: Operating System :: OS Independent
Classifier: Programming Language :: Python :: 3
Classifier: Programming Language :: Python :: 3.8
Classifier: Programming Language :: Python :: 3.9
Classifier: Programming Language :: Python :: 3.10
Classifier: Programming Language :: Python :: 3.11
Classifier: Programming Language :: Python :: 3.12
Classifier: Topic :: Security
Classifier: Topic :: Software Development :: Libraries :: Python Modules
Requires-Python: >=3.8
License-File: LICENSE
Requires-Dist: pydantic<3.0.0,>=2.0.0
Requires-Dist: PyJWT[cryptography]<3.0.0,>=2.8.0
Requires-Dist: httpx<1.0.0,>=0.20.0
Requires-Dist: cryptography<42.0.0,>=3.4.0
Provides-Extra: dev
Requires-Dist: pytest>=6.0; extra == "dev"
Requires-Dist: pytest-asyncio>=0.18.0; extra == "dev"
Requires-Dist: pytest-cov>=3.0.0; extra == "dev"
Requires-Dist: black>=22.0.0; extra == "dev"
Requires-Dist: flake8>=4.0.0; extra == "dev"
Requires-Dist: mypy>=0.950; extra == "dev"
Provides-Extra: test
Requires-Dist: pytest>=6.0; extra == "test"
Requires-Dist: pytest-asyncio>=0.18.0; extra == "test"
Requires-Dist: httpx-mock>=0.7.0; extra == "test"
Dynamic: author
Dynamic: home-page
Dynamic: license-file
Dynamic: requires-python
